runpod_enhanced/__init__.py
runpod_enhanced/error.py
runpod_enhanced/http_client.py
runpod_enhanced/user_agent.py
runpod_enhanced/version.py
runpod_enhanced/api/__init__.py
runpod_enhanced/api/ctl_commands.py
runpod_enhanced/api/graphql.py
runpod_enhanced/api/mutations/__init__.py
runpod_enhanced/api/mutations/container_register_auth.py
runpod_enhanced/api/mutations/endpoints.py
runpod_enhanced/api/mutations/pods.py
runpod_enhanced/api/mutations/templates.py
runpod_enhanced/api/mutations/user.py
runpod_enhanced/api/queries/__init__.py
runpod_enhanced/api/queries/endpoints.py
runpod_enhanced/api/queries/gpus.py
runpod_enhanced/api/queries/pods.py
runpod_enhanced/api/queries/user.py
runpod_enhanced/cli/__init__.py
runpod_enhanced/cli/entry.py
runpod_enhanced/cli/groups/__init__.py
runpod_enhanced/cli/groups/config/__init__.py
runpod_enhanced/cli/groups/config/commands.py
runpod_enhanced/cli/groups/config/functions.py
runpod_enhanced/cli/groups/exec/__init__.py
runpod_enhanced/cli/groups/exec/commands.py
runpod_enhanced/cli/groups/exec/functions.py
runpod_enhanced/cli/groups/exec/helpers.py
runpod_enhanced/cli/groups/pod/__init__.py
runpod_enhanced/cli/groups/pod/commands.py
runpod_enhanced/cli/groups/project/__init__.py
runpod_enhanced/cli/groups/project/commands.py
runpod_enhanced/cli/groups/project/functions.py
runpod_enhanced/cli/groups/project/helpers.py
runpod_enhanced/cli/groups/ssh/__init__.py
runpod_enhanced/cli/groups/ssh/commands.py
runpod_enhanced/cli/groups/ssh/functions.py
runpod_enhanced/cli/utils/__init__.py
runpod_enhanced/cli/utils/rp_info.py
runpod_enhanced/cli/utils/rp_runpodignore.py
runpod_enhanced/cli/utils/rp_sync.py
runpod_enhanced/cli/utils/rp_userspace.py
runpod_enhanced/cli/utils/ssh_cmd.py
runpod_enhanced/endpoint/__init__.py
runpod_enhanced/endpoint/helpers.py
runpod_enhanced/endpoint/runner.py
runpod_enhanced/endpoint/asyncio/__init__.py
runpod_enhanced/endpoint/asyncio/asyncio_runner.py
runpod_enhanced/serverless/__init__.py
runpod_ext-0.1.5.dist-info/LICENSE
runpod_ext-0.1.5.dist-info/METADATA
runpod_ext-0.1.5.dist-info/WHEEL
runpod_ext-0.1.5.dist-info/entry_points.txt
runpod_ext-0.1.5.dist-info/top_level.txt
runpod_ext-0.1.5.dist-info/RECORD
